skyset/__init__.py
pyskyset-0.1.0.dist-info/METADATA
pyskyset-0.1.0.dist-info/WHEEL
pyskyset-0.1.0.dist-info/entry_points.txt
pyskyset-0.1.0.dist-info/RECORD
