Metadata-Version: 2.4
Name: pyskyset
Version: 0.1.0
Summary: A Python client for Skyset
Requires-Python: >=3.12
Requires-Dist: pyyaml>=6.0.3
